pgpigeon/__init__.py
pgpigeon/common.py
pgpigeon/constants.py
pgpigeon/context_models.py
pgpigeon/interpreter.py
pgpigeon/modules.py
pgpigeon/pgnest.py
pgpigeon/pgpigeon.py
pgpigeon/pgscript.py
pgpigeon/pigeon_cli.py
pgpigeon/commands/__init__.py
pgpigeon/commands/configure.py
pgpigeon/commands/create_scripts.py
pgpigeon/commands/create_triggers.py
pgpigeon/commands/sample_code.py
pgpigeon-1.1.5.dist-info/LICENSE
pgpigeon-1.1.5.dist-info/METADATA
pgpigeon-1.1.5.dist-info/WHEEL
pgpigeon-1.1.5.dist-info/entry_points.txt
pgpigeon-1.1.5.dist-info/top_level.txt
pgpigeon-1.1.5.dist-info/RECORD
