Metadata-Version: 2.1
Name: pgpigeon
Version: 1.1.5
Summary: This package help to implement realtime db notifications.
Author-email: Dinesh Kushwaha <2kush.dinesh@gmail.com>
License: MIT License
Project-URL: Homepage, https://github.com/dinesh-kushwaha/pypigeon
Project-URL: Bug Tracker, https://github.com/pypa/sampleproject/issues
Keywords: python,postgresql,realtime,notification,pg_notify,channel
Classifier: Programming Language :: Python :: 3
Classifier: License :: OSI Approved :: MIT License
Classifier: Operating System :: OS Independent
Requires-Python: >=3.6
License-File: LICENSE
Requires-Dist: psycopg2 (>=2.9.3)
